fluidattacks_etl_utils/__init__.py
fluidattacks_etl_utils/bug.py
fluidattacks_etl_utils/date_range.py
fluidattacks_etl_utils/decode.py
fluidattacks_etl_utils/env_var.py
fluidattacks_etl_utils/handle_errors.py
fluidattacks_etl_utils/mutable.py
fluidattacks_etl_utils/natural.py
fluidattacks_etl_utils/paginate.py
fluidattacks_etl_utils/parallel.py
fluidattacks_etl_utils/process.py
fluidattacks_etl_utils/py.typed
fluidattacks_etl_utils/retry.py
fluidattacks_etl_utils/smash.py
fluidattacks_etl_utils/table_utils.py
fluidattacks_etl_utils/typing.py
fluidattacks_etl_utils/unit_helpers.py
fluidattacks_etl_utils/secrets/__init__.py
fluidattacks_etl_utils/secrets/_core.py
fluidattacks_etl_utils/secrets/_integrates.py
fluidattacks_etl_utils/secrets/_snowflake.py
fluidattacks_etl_utils/secrets/_zoho_leads.py
fluidattacks_etl_utils-3.0.0.dist-info/WHEEL
fluidattacks_etl_utils-3.0.0.dist-info/METADATA
fluidattacks_etl_utils-3.0.0.dist-info/RECORD
