Metadata-Version: 2.4
Name: fluidattacks_etl_utils
Version: 3.0.0
Summary: Common etl utils
Author-email: Product Team <development@fluidattacks.com>
Requires-Python: >=3.11
Classifier: License :: OSI Approved :: MIT License
Requires-Dist: fa-purity >=2.5.2, <3.0.0
Requires-Dist: gitpython >=3.1.44, <4.0.0
Requires-Dist: requests >=2.32.4, <3.0.0
Requires-Dist: pathos >=0.3.1, <0.4.0
Requires-Dist: python-dateutil >=2.9.0, <3.0.0
Requires-Dist: redshift-client >=9.0.0, <10.0.0
